visorRobot/__init__.py
visorRobot/visor.py
visorRobot04-0.0.1.dist-info/METADATA
visorRobot04-0.0.1.dist-info/WHEEL
visorRobot04-0.0.1.dist-info/top_level.txt
visorRobot04-0.0.1.dist-info/RECORD
